setup.py
Promcode/Promcode.py
Promcode/__init__.py
Promcode.egg-info/PKG-INFO
Promcode.egg-info/SOURCES.txt
Promcode.egg-info/dependency_links.txt
Promcode.egg-info/top_level.txt