Metadata-Version: 2.1
Name: Promcode
Version: 8.0
Summary: By Golden In telegram @rrrrrf
Author: Programmer Golden 
Classifier: Programming Language :: Python :: 3
Classifier: Operating System :: OS Independent
Classifier: License :: OSI Approved :: MIT License
